path_add_jlussier/__init__.py
path_add_jlussier/add_parent_path.py
path_add_jlussier-0.0.1.dist-info/METADATA
path_add_jlussier-0.0.1.dist-info/WHEEL
path_add_jlussier-0.0.1.dist-info/licenses/LICENSE
path_add_jlussier-0.0.1.dist-info/RECORD
